aliyunsdkpaifeaturestore/__init__.py
aliyunsdkpaifeaturestore/request/__init__.py
aliyunsdkpaifeaturestore/request/v20230621/CheckInstanceDatasourceRequest.py
aliyunsdkpaifeaturestore/request/v20230621/CheckModelFeatureFGFeatureRequest.py
aliyunsdkpaifeaturestore/request/v20230621/CreateDatasourceRequest.py
aliyunsdkpaifeaturestore/request/v20230621/CreateFeatureEntityRequest.py
aliyunsdkpaifeaturestore/request/v20230621/CreateFeatureViewRequest.py
aliyunsdkpaifeaturestore/request/v20230621/CreateInstanceRequest.py
aliyunsdkpaifeaturestore/request/v20230621/CreateLLMConfigRequest.py
aliyunsdkpaifeaturestore/request/v20230621/CreateLabelTableRequest.py
aliyunsdkpaifeaturestore/request/v20230621/CreateModelFeatureRequest.py
aliyunsdkpaifeaturestore/request/v20230621/CreateProjectRequest.py
aliyunsdkpaifeaturestore/request/v20230621/CreateServiceIdentityRoleRequest.py
aliyunsdkpaifeaturestore/request/v20230621/DeleteDatasourceRequest.py
aliyunsdkpaifeaturestore/request/v20230621/DeleteFeatureEntityRequest.py
aliyunsdkpaifeaturestore/request/v20230621/DeleteFeatureViewRequest.py
aliyunsdkpaifeaturestore/request/v20230621/DeleteLLMConfigRequest.py
aliyunsdkpaifeaturestore/request/v20230621/DeleteLabelTableRequest.py
aliyunsdkpaifeaturestore/request/v20230621/DeleteModelFeatureRequest.py
aliyunsdkpaifeaturestore/request/v20230621/DeleteProjectRequest.py
aliyunsdkpaifeaturestore/request/v20230621/ExportModelFeatureTrainingSetTableRequest.py
aliyunsdkpaifeaturestore/request/v20230621/GetDatasourceRequest.py
aliyunsdkpaifeaturestore/request/v20230621/GetDatasourceTableRequest.py
aliyunsdkpaifeaturestore/request/v20230621/GetFeatureEntityRequest.py
aliyunsdkpaifeaturestore/request/v20230621/GetFeatureViewRequest.py
aliyunsdkpaifeaturestore/request/v20230621/GetInstanceRequest.py
aliyunsdkpaifeaturestore/request/v20230621/GetLLMConfigRequest.py
aliyunsdkpaifeaturestore/request/v20230621/GetLabelTableRequest.py
aliyun_python_sdk_paifeaturestore-1.0.19.dist-info/LICENSE
aliyun_python_sdk_paifeaturestore-1.0.19.dist-info/METADATA
aliyun_python_sdk_paifeaturestore-1.0.19.dist-info/WHEEL
aliyun_python_sdk_paifeaturestore-1.0.19.dist-info/top_level.txt
aliyun_python_sdk_paifeaturestore-1.0.19.dist-info/RECORD
